{
    "Metadata": {
        "title": ""
    },
    "Header": {
        "links": ["الصفحة الرئيسية ", "حول", "تجربة", "مشاريع", "اتصالات"]
    },
    "Main": {
        "Home": {
            "name": "Alef A. Araujo",
            "profession": "مطور ويب"
        },
        "About": {
            "about_me": "ْعَنِّي",
            "paragraph_1": "اسمي ألف وأنا متحمس للتقنيات الجديدة. أدرك أهمية التقنيات التي تم دمجها بالفعل في السوق، ولكنني أفسح المجال دائمًا لشيء جديد. لقد بدأت العمل في المنطقة في نهاية عام 2020، حيث قمت بدراسة أساسيات تطوير الويب.",
            "paragraph_2": "أدرس حاليًا تحليل وتطوير الأنظمة وأركز على توسيع مهاراتي."
        }
    }
}